family_ai_voice_assistant/__init__.py
family_ai_voice_assistant/core/__init__.py
family_ai_voice_assistant/core/assistants/__init__.py
family_ai_voice_assistant/core/assistants/assistant_console_client.py
family_ai_voice_assistant/core/assistants/assistant_with_api.py
family_ai_voice_assistant/core/assistants/basic_assistant.py
family_ai_voice_assistant/core/client_register.py
family_ai_voice_assistant/core/client_selector.py
family_ai_voice_assistant/core/clients/__init__.py
family_ai_voice_assistant/core/clients/assistant_client.py
family_ai_voice_assistant/core/clients/chat_session_client.py
family_ai_voice_assistant/core/clients/client_manager.py
family_ai_voice_assistant/core/clients/file_store_client.py
family_ai_voice_assistant/core/clients/greeting_client.py
family_ai_voice_assistant/core/clients/history_store_client.py
family_ai_voice_assistant/core/clients/listening_client.py
family_ai_voice_assistant/core/clients/llm_client.py
family_ai_voice_assistant/core/clients/play_sound_client.py
family_ai_voice_assistant/core/clients/recognition_client.py
family_ai_voice_assistant/core/clients/speech_client.py
family_ai_voice_assistant/core/clients/waker_client.py
family_ai_voice_assistant/core/clients/watiable_result_client.py
family_ai_voice_assistant/core/configs/__init__.py
family_ai_voice_assistant/core/configs/_config_handlers/__init__.py
family_ai_voice_assistant/core/configs/_config_handlers/_config_handler.py
family_ai_voice_assistant/core/configs/_config_handlers/_config_handler_factory.py
family_ai_voice_assistant/core/configs/_config_handlers/_yaml_config_handler.py
family_ai_voice_assistant/core/configs/assistant_api_config.py
family_ai_voice_assistant/core/configs/chat_session_config.py
family_ai_voice_assistant/core/configs/config.py
family_ai_voice_assistant/core/configs/file_store_config.py
family_ai_voice_assistant/core/configs/general_config.py
family_ai_voice_assistant/core/configs/history_store_config.py
family_ai_voice_assistant_core-0.1.0.dist-info/METADATA
family_ai_voice_assistant_core-0.1.0.dist-info/WHEEL
family_ai_voice_assistant_core-0.1.0.dist-info/entry_points.txt
family_ai_voice_assistant_core-0.1.0.dist-info/RECORD
