Metadata-Version: 2.1
Name: family-ai-voice-assistant-core
Version: 0.1.0
Summary: Core library for home smart speakers based on large language models (LLM).
Home-page: https://github.com/augaria/family-ai-voice-assistant/tree/augaria/dev/src/family-ai-voice-assistant-core
License: MIT
Author: Augaria
Author-email: augaria@163.com
Requires-Python: >=3.9,<4.0
Classifier: License :: OSI Approved :: MIT License
Classifier: Programming Language :: Python :: 3
Classifier: Programming Language :: Python :: 3.9
Classifier: Programming Language :: Python :: 3.10
Classifier: Programming Language :: Python :: 3.11
Classifier: Programming Language :: Python :: 3.12
Classifier: Programming Language :: Python :: 3.13
Requires-Dist: Jinja2
Requires-Dist: colorama
Requires-Dist: docstring-parser
Requires-Dist: evdev ; sys_platform == "linux"
Requires-Dist: flask
Requires-Dist: opentelemetry-api
Requires-Dist: opentelemetry-exporter-otlp
Requires-Dist: opentelemetry-sdk
Requires-Dist: pymongo
Requires-Dist: pytz
Requires-Dist: pyyaml
Requires-Dist: scipy
Requires-Dist: tzlocal
Project-URL: Repository, https://github.com/augaria/family-ai-voice-assistant/tree/augaria/dev/src/family-ai-voice-assistant-core
